pipedrive/__init__.py
pipedrive/deal.py
pipedrive/filter.py
pipedrive/mixins.py
pipedrive/organization.py
pipedrive/person.py
pipedrive/utils.py
py_pipedrive_api-0.2.1.dist-info/LICENSE
py_pipedrive_api-0.2.1.dist-info/METADATA
py_pipedrive_api-0.2.1.dist-info/WHEEL
py_pipedrive_api-0.2.1.dist-info/top_level.txt
py_pipedrive_api-0.2.1.dist-info/RECORD
